{
    "v1": [
        {
            "tool_version": "232.0.20230509.135236-eap01",
            "error_mismatch": true,
            "project": null,
            "timestamp": 1684209128.558631,
            "elapsed_time": 696.012451171875,
            "x64": true,
            "actual_files_count": 1013,
            "expected_files_count": 1013
        },
        {
            "tool_version": "232.0.20230509.135236-eap01",
            "error_mismatch": true,
            "project": null,
            "timestamp": 1684295391.451663,
            "elapsed_time": 614.4793035984039,
            "x64": true,
            "actual_files_count": 1013,
            "expected_files_count": 1013
        },
        {
            "tool_version": "232.0.20230509.135236-eap01",
            "error_mismatch": false,
            "project": null,
            "timestamp": 1684381858.029478,
            "elapsed_time": 686.6764855384827,
            "x64": true,
            "actual_files_count": 1013,
            "expected_files_count": 1013
        },
        {
            "tool_version": "232.0.20230509.135236-eap01",
            "error_mismatch": false,
            "project": null,
            "timestamp": 1684469008.670229,
            "elapsed_time": 907.610963344574,
            "x64": true,
            "actual_files_count": 1013,
            "expected_files_count": 1013
        },
        {
            "tool_version": "232.0.20230509.135236-eap01",
            "error_mismatch": false,
            "project": null,
            "timestamp": 1684554717.585761,
            "elapsed_time": 742.8931791782379,
            "x64": true,
            "actual_files_count": 1013,
            "expected_files_count": 1013
        },
        {
            "tool_version": "232.0.20230509.135236-eap01",
            "error_mismatch": false,
            "project": null,
            "timestamp": 1684641006.628266,
            "elapsed_time": 668.9734065532684,
            "x64": true,
            "actual_files_count": 1013,
            "expected_files_count": 1013
        },
        {
            "tool_version": "232.0.20230509.135236-eap01",
            "error_mismatch": false,
            "project": null,
            "timestamp": 1684814324.751231,
            "elapsed_time": 830.1052258014679,
            "x64": true,
            "actual_files_count": 1013,
            "expected_files_count": 1013,
            "repo_url": "https://github.com/cemu-project/Cemu",
            "commit_ref": "eda4cf4b241d56c5c16f6aa4d135b8a269676a76",
            "commit_message": "Fix UI crash on Windows (#813)\n\n",
            "commit_timestamp": 1683811665.0
        },
        {
            "tool_version": "232.0.20230509.135236-eap01",
            "error_mismatch": false,
            "project": null,
            "timestamp": 1684901160.325864,
            "elapsed_time": 936.4639828205109,
            "x64": true,
            "actual_files_count": 1013,
            "expected_files_count": 1013,
            "repo_url": "https://github.com/cemu-project/Cemu",
            "commit_ref": "eda4cf4b241d56c5c16f6aa4d135b8a269676a76",
            "commit_message": "Fix UI crash on Windows (#813)\n\n",
            "commit_timestamp": 1683811665.0
        },
        {
            "tool_version": "232.0.20230517.90859-eap02",
            "error_mismatch": false,
            "project": null,
            "timestamp": 1684986641.250375,
            "elapsed_time": 623.3243429660797,
            "x64": true,
            "actual_files_count": 1013,
            "expected_files_count": 1013,
            "repo_url": "https://github.com/cemu-project/Cemu",
            "commit_ref": "eda4cf4b241d56c5c16f6aa4d135b8a269676a76",
            "commit_message": "Fix UI crash on Windows (#813)\n\n",
            "commit_timestamp": 1683811665.0
        },
        {
            "tool_version": "232.0.20230517.90859-eap02",
            "error_mismatch": false,
            "project": null,
            "timestamp": 1685073024.491158,
            "elapsed_time": 649.4045712947845,
            "x64": true,
            "actual_files_count": 1013,
            "expected_files_count": 1013,
            "repo_url": "https://github.com/cemu-project/Cemu",
            "commit_ref": "eda4cf4b241d56c5c16f6aa4d135b8a269676a76",
            "commit_message": "Fix UI crash on Windows (#813)\n\n",
            "commit_timestamp": 1683811665.0
        },
        {
            "tool_version": "232.0.20230517.90859-eap02",
            "error_mismatch": false,
            "project": null,
            "timestamp": 1685202687.249822,
            "elapsed_time": 727.230259180069,
            "x64": true,
            "actual_files_count": 1013,
            "expected_files_count": 1013,
            "repo_url": "https://github.com/cemu-project/Cemu",
            "commit_ref": "eda4cf4b241d56c5c16f6aa4d135b8a269676a76",
            "commit_message": "Fix UI crash on Windows (#813)\n\n",
            "commit_timestamp": 1683811665.0
        },
        {
            "tool_version": "232.0.20230517.90859-eap02",
            "error_mismatch": false,
            "project": null,
            "timestamp": 1685245115.879115,
            "elapsed_time": 702.858199596405,
            "x64": true,
            "actual_files_count": 1013,
            "expected_files_count": 1013,
            "repo_url": "https://github.com/cemu-project/Cemu",
            "commit_ref": "eda4cf4b241d56c5c16f6aa4d135b8a269676a76",
            "commit_message": "Fix UI crash on Windows (#813)\n\n",
            "commit_timestamp": 1683811665.0
        },
        {
            "tool_version": "232.0.20230517.90859-eap02",
            "error_mismatch": false,
            "project": null,
            "timestamp": 1685288592.600853,
            "elapsed_time": 766.3404574394226,
            "x64": true,
            "actual_files_count": 1013,
            "expected_files_count": 1013,
            "repo_url": "https://github.com/cemu-project/Cemu",
            "commit_ref": "eda4cf4b241d56c5c16f6aa4d135b8a269676a76",
            "commit_message": "Fix UI crash on Windows (#813)\n\n",
            "commit_timestamp": 1683811665.0
        },
        {
            "tool_version": "232.0.20230517.90859-eap02",
            "error_mismatch": false,
            "project": null,
            "timestamp": 1685331522.115347,
            "elapsed_time": 686.9678659439087,
            "x64": true,
            "actual_files_count": 1013,
            "expected_files_count": 1013,
            "repo_url": "https://github.com/cemu-project/Cemu",
            "commit_ref": "eda4cf4b241d56c5c16f6aa4d135b8a269676a76",
            "commit_message": "Fix UI crash on Windows (#813)\n\n",
            "commit_timestamp": 1683811665.0
        },
        {
            "tool_version": "232.0.20230517.90859-eap02",
            "error_mismatch": false,
            "project": null,
            "timestamp": 1685374988.931096,
            "elapsed_time": 781.8720819950104,
            "x64": true,
            "actual_files_count": 1013,
            "expected_files_count": 1013,
            "repo_url": "https://github.com/cemu-project/Cemu",
            "commit_ref": "eda4cf4b241d56c5c16f6aa4d135b8a269676a76",
            "commit_message": "Fix UI crash on Windows (#813)\n\n",
            "commit_timestamp": 1683811665.0
        },
        {
            "tool_version": "232.0.20230517.90859-eap02",
            "error_mismatch": false,
            "project": null,
            "timestamp": 1685417927.041541,
            "elapsed_time": 690.3947508335114,
            "x64": true,
            "actual_files_count": 1013,
            "expected_files_count": 1013,
            "repo_url": "https://github.com/cemu-project/Cemu",
            "commit_ref": "eda4cf4b241d56c5c16f6aa4d135b8a269676a76",
            "commit_message": "Fix UI crash on Windows (#813)\n\n",
            "commit_timestamp": 1683811665.0
        },
        {
            "tool_version": "232.0.20230517.90859-eap02",
            "error_mismatch": false,
            "project": null,
            "timestamp": 1685461109.160378,
            "elapsed_time": 621.5613861083984,
            "x64": true,
            "actual_files_count": 1013,
            "expected_files_count": 1013,
            "repo_url": "https://github.com/cemu-project/Cemu",
            "commit_ref": "eda4cf4b241d56c5c16f6aa4d135b8a269676a76",
            "commit_message": "Fix UI crash on Windows (#813)\n\n",
            "commit_timestamp": 1683811665.0
        },
        {
            "tool_version": "232.0.20230517.90859-eap02",
            "error_mismatch": false,
            "project": null,
            "timestamp": 1685504537.728736,
            "elapsed_time": 716.0372021198273,
            "x64": true,
            "actual_files_count": 1013,
            "expected_files_count": 1013,
            "repo_url": "https://github.com/cemu-project/Cemu",
            "commit_ref": "eda4cf4b241d56c5c16f6aa4d135b8a269676a76",
            "commit_message": "Fix UI crash on Windows (#813)\n\n",
            "commit_timestamp": 1683811665.0
        },
        {
            "tool_version": "232.0.20230517.90859-eap02",
            "error_mismatch": false,
            "project": null,
            "timestamp": 1685548217.104374,
            "elapsed_time": 938.6295695304871,
            "x64": true,
            "actual_files_count": 1013,
            "expected_files_count": 1013,
            "repo_url": "https://github.com/cemu-project/Cemu",
            "commit_ref": "eda4cf4b241d56c5c16f6aa4d135b8a269676a76",
            "commit_message": "Fix UI crash on Windows (#813)\n\n",
            "commit_timestamp": 1683811665.0
        },
        {
            "tool_version": "232.0.20230517.90859-eap02",
            "error_mismatch": false,
            "project": null,
            "timestamp": 1685591574.929203,
            "elapsed_time": 618.0644452571869,
            "x64": true,
            "actual_files_count": 1013,
            "expected_files_count": 1013,
            "repo_url": "https://github.com/cemu-project/Cemu",
            "commit_ref": "eda4cf4b241d56c5c16f6aa4d135b8a269676a76",
            "commit_message": "Fix UI crash on Windows (#813)\n\n",
            "commit_timestamp": 1683811665.0
        },
        {
            "tool_version": "232.0.20230517.90859-eap02",
            "error_mismatch": false,
            "project": null,
            "timestamp": 1685634502.604613,
            "elapsed_time": 925.9061949253082,
            "x64": true,
            "actual_files_count": 1013,
            "expected_files_count": 1013,
            "repo_url": "https://github.com/cemu-project/Cemu",
            "commit_ref": "eda4cf4b241d56c5c16f6aa4d135b8a269676a76",
            "commit_message": "Fix UI crash on Windows (#813)\n\n",
            "commit_timestamp": 1683811665.0
        },
        {
            "tool_version": "232.0.20230517.90859-eap02",
            "error_mismatch": false,
            "project": null,
            "timestamp": 1685677050.384499,
            "elapsed_time": 679.0503776073456,
            "x64": true,
            "actual_files_count": 1013,
            "expected_files_count": 1013,
            "repo_url": "https://github.com/cemu-project/Cemu",
            "commit_ref": "eda4cf4b241d56c5c16f6aa4d135b8a269676a76",
            "commit_message": "Fix UI crash on Windows (#813)\n\n",
            "commit_timestamp": 1683811665.0
        },
        {
            "tool_version": "232.0.20230517.90859-eap02",
            "error_mismatch": false,
            "project": null,
            "timestamp": 1685720571.18389,
            "elapsed_time": 809.0811977386475,
            "x64": true,
            "actual_files_count": 1013,
            "expected_files_count": 1013,
            "repo_url": "https://github.com/cemu-project/Cemu",
            "commit_ref": "eda4cf4b241d56c5c16f6aa4d135b8a269676a76",
            "commit_message": "Fix UI crash on Windows (#813)\n\n",
            "commit_timestamp": 1683811665.0
        },
        {
            "tool_version": "232.0.20230517.90859-eap02",
            "error_mismatch": false,
            "project": null,
            "timestamp": 1685763379.193343,
            "elapsed_time": 661.2107663154602,
            "x64": true,
            "actual_files_count": 1013,
            "expected_files_count": 1013,
            "repo_url": "https://github.com/cemu-project/Cemu",
            "commit_ref": "eda4cf4b241d56c5c16f6aa4d135b8a269676a76",
            "commit_message": "Fix UI crash on Windows (#813)\n\n",
            "commit_timestamp": 1683811665.0
        },
        {
            "tool_version": "232.0.20230517.90859-eap02",
            "error_mismatch": false,
            "project": null,
            "timestamp": 1685806959.566471,
            "elapsed_time": 786.5682151317596,
            "x64": true,
            "actual_files_count": 1013,
            "expected_files_count": 1013,
            "repo_url": "https://github.com/cemu-project/Cemu",
            "commit_ref": "eda4cf4b241d56c5c16f6aa4d135b8a269676a76",
            "commit_message": "Fix UI crash on Windows (#813)\n\n",
            "commit_timestamp": 1683811665.0
        },
        {
            "tool_version": "232.0.20230517.90859-eap02",
            "error_mismatch": false,
            "project": null,
            "timestamp": 1685850508.686306,
            "elapsed_time": 693.037841796875,
            "x64": true,
            "actual_files_count": 1013,
            "expected_files_count": 1013,
            "repo_url": "https://github.com/cemu-project/Cemu",
            "commit_ref": "eda4cf4b241d56c5c16f6aa4d135b8a269676a76",
            "commit_message": "Fix UI crash on Windows (#813)\n\n",
            "commit_timestamp": 1683811665.0
        },
        {
            "tool_version": "232.0.20230517.90859-eap02",
            "error_mismatch": false,
            "project": null,
            "timestamp": 1685893878.945647,
            "elapsed_time": 939.7528071403503,
            "x64": true,
            "actual_files_count": 1013,
            "expected_files_count": 1013,
            "repo_url": "https://github.com/cemu-project/Cemu",
            "commit_ref": "eda4cf4b241d56c5c16f6aa4d135b8a269676a76",
            "commit_message": "Fix UI crash on Windows (#813)\n\n",
            "commit_timestamp": 1683811665.0
        },
        {
            "tool_version": "232.0.20230517.90859-eap02",
            "error_mismatch": false,
            "project": null,
            "timestamp": 1685936611.306256,
            "elapsed_time": 799.2422952651978,
            "x64": true,
            "actual_files_count": 1013,
            "expected_files_count": 1013,
            "repo_url": "https://github.com/cemu-project/Cemu",
            "commit_ref": "eda4cf4b241d56c5c16f6aa4d135b8a269676a76",
            "commit_message": "Fix UI crash on Windows (#813)\n\n",
            "commit_timestamp": 1683811665.0
        },
        {
            "tool_version": "232.0.20230517.90859-eap02",
            "error_mismatch": true,
            "project": null,
            "timestamp": 1685979538.564465,
            "elapsed_time": 712.3942782878876,
            "x64": true,
            "actual_files_count": 1013,
            "expected_files_count": 1013,
            "repo_url": "https://github.com/cemu-project/Cemu",
            "commit_ref": "eda4cf4b241d56c5c16f6aa4d135b8a269676a76",
            "commit_message": "Fix UI crash on Windows (#813)\n\n",
            "commit_timestamp": 1683811665.0
        },
        {
            "tool_version": "232.0.20230517.90859-eap02",
            "error_mismatch": false,
            "project": null,
            "timestamp": 1686022956.478209,
            "elapsed_time": 685.9289345741272,
            "x64": true,
            "actual_files_count": 1013,
            "expected_files_count": 1013,
            "repo_url": "https://github.com/cemu-project/Cemu",
            "commit_ref": "eda4cf4b241d56c5c16f6aa4d135b8a269676a76",
            "commit_message": "Fix UI crash on Windows (#813)\n\n",
            "commit_timestamp": 1683811665.0
        },
        {
            "tool_version": "232.0.20230531.134455-eap03",
            "error_mismatch": false,
            "project": null,
            "timestamp": 1686066191.375935,
            "elapsed_time": 914.1716029644012,
            "x64": true,
            "actual_files_count": 1013,
            "expected_files_count": 1013,
            "repo_url": "https://github.com/cemu-project/Cemu",
            "commit_ref": "eda4cf4b241d56c5c16f6aa4d135b8a269676a76",
            "commit_message": "Fix UI crash on Windows (#813)\n\n",
            "commit_timestamp": 1683811665.0
        },
        {
            "tool_version": "232.0.20230531.134455-eap03",
            "error_mismatch": false,
            "project": null,
            "timestamp": 1686109653.613051,
            "elapsed_time": 976.3586235046387,
            "x64": true,
            "actual_files_count": 1013,
            "expected_files_count": 1013,
            "repo_url": "https://github.com/cemu-project/Cemu",
            "commit_ref": "eda4cf4b241d56c5c16f6aa4d135b8a269676a76",
            "commit_message": "Fix UI crash on Windows (#813)\n\n",
            "commit_timestamp": 1683811665.0
        },
        {
            "tool_version": "232.0.20230531.134455-eap03",
            "error_mismatch": false,
            "project": null,
            "timestamp": 1686152243.38351,
            "elapsed_time": 743.6043083667755,
            "x64": true,
            "actual_files_count": 1013,
            "expected_files_count": 1013,
            "repo_url": "https://github.com/cemu-project/Cemu",
            "commit_ref": "eda4cf4b241d56c5c16f6aa4d135b8a269676a76",
            "commit_message": "Fix UI crash on Windows (#813)\n\n",
            "commit_timestamp": 1683811665.0
        },
        {
            "tool_version": "232.0.20230531.134455-eap03",
            "error_mismatch": false,
            "project": null,
            "timestamp": 1686195727.319984,
            "elapsed_time": 741.1555950641632,
            "x64": true,
            "actual_files_count": 1013,
            "expected_files_count": 1013,
            "repo_url": "https://github.com/cemu-project/Cemu",
            "commit_ref": "eda4cf4b241d56c5c16f6aa4d135b8a269676a76",
            "commit_message": "Fix UI crash on Windows (#813)\n\n",
            "commit_timestamp": 1683811665.0
        },
        {
            "tool_version": "232.0.20230531.134455-eap03",
            "error_mismatch": false,
            "project": null,
            "timestamp": 1686238669.29278,
            "elapsed_time": 716.8714873790741,
            "x64": true,
            "actual_files_count": 1013,
            "expected_files_count": 1013,
            "repo_url": "https://github.com/cemu-project/Cemu",
            "commit_ref": "eda4cf4b241d56c5c16f6aa4d135b8a269676a76",
            "commit_message": "Fix UI crash on Windows (#813)\n\n",
            "commit_timestamp": 1683811665.0
        },
        {
            "tool_version": "232.0.20230531.134455-eap03",
            "error_mismatch": false,
            "project": null,
            "timestamp": 1686282157.506321,
            "elapsed_time": 734.4219071865082,
            "x64": true,
            "actual_files_count": 1013,
            "expected_files_count": 1013,
            "repo_url": "https://github.com/cemu-project/Cemu",
            "commit_ref": "eda4cf4b241d56c5c16f6aa4d135b8a269676a76",
            "commit_message": "Fix UI crash on Windows (#813)\n\n",
            "commit_timestamp": 1683811665.0
        },
        {
            "tool_version": "232.0.20230531.134455-eap03",
            "error_mismatch": false,
            "project": null,
            "timestamp": 1686325051.329874,
            "elapsed_time": 824.52050614357,
            "x64": true,
            "actual_files_count": 1013,
            "expected_files_count": 1013,
            "repo_url": "https://github.com/cemu-project/Cemu",
            "commit_ref": "eda4cf4b241d56c5c16f6aa4d135b8a269676a76",
            "commit_message": "Fix UI crash on Windows (#813)\n\n",
            "commit_timestamp": 1683811665.0
        },
        {
            "tool_version": "232.0.20230531.134455-eap03",
            "error_mismatch": false,
            "project": null,
            "timestamp": 1686368249.384097,
            "elapsed_time": 841.9888010025024,
            "x64": true,
            "actual_files_count": 1013,
            "expected_files_count": 1013,
            "repo_url": "https://github.com/cemu-project/Cemu",
            "commit_ref": "eda4cf4b241d56c5c16f6aa4d135b8a269676a76",
            "commit_message": "Fix UI crash on Windows (#813)\n\n",
            "commit_timestamp": 1683811665.0
        },
        {
            "tool_version": "232.0.20230531.134455-eap03",
            "error_mismatch": false,
            "project": null,
            "timestamp": 1686411393.698867,
            "elapsed_time": 783.3448786735535,
            "x64": true,
            "actual_files_count": 1013,
            "expected_files_count": 1013,
            "repo_url": "https://github.com/cemu-project/Cemu",
            "commit_ref": "eda4cf4b241d56c5c16f6aa4d135b8a269676a76",
            "commit_message": "Fix UI crash on Windows (#813)\n\n",
            "commit_timestamp": 1683811665.0
        },
        {
            "tool_version": "232.0.20230531.134455-eap03",
            "error_mismatch": false,
            "project": null,
            "timestamp": 1686455228.315471,
            "elapsed_time": 780.247674703598,
            "x64": true,
            "actual_files_count": 1013,
            "expected_files_count": 1013,
            "repo_url": "https://github.com/cemu-project/Cemu",
            "commit_ref": "eda4cf4b241d56c5c16f6aa4d135b8a269676a76",
            "commit_message": "Fix UI crash on Windows (#813)\n\n",
            "commit_timestamp": 1683811665.0
        },
        {
            "tool_version": "232.0.20230531.134455-eap03",
            "error_mismatch": false,
            "project": null,
            "timestamp": 1686497855.436511,
            "elapsed_time": 718.2891175746918,
            "x64": true,
            "actual_files_count": 1013,
            "expected_files_count": 1013,
            "repo_url": "https://github.com/cemu-project/Cemu",
            "commit_ref": "eda4cf4b241d56c5c16f6aa4d135b8a269676a76",
            "commit_message": "Fix UI crash on Windows (#813)\n\n",
            "commit_timestamp": 1683811665.0
        },
        {
            "tool_version": "232.0.20230531.134455-eap03",
            "error_mismatch": false,
            "project": null,
            "timestamp": 1686541410.317477,
            "elapsed_time": 743.6609144210815,
            "x64": true,
            "actual_files_count": 1013,
            "expected_files_count": 1013,
            "repo_url": "https://github.com/cemu-project/Cemu",
            "commit_ref": "eda4cf4b241d56c5c16f6aa4d135b8a269676a76",
            "commit_message": "Fix UI crash on Windows (#813)\n\n",
            "commit_timestamp": 1683811665.0
        },
        {
            "tool_version": "232.0.20230608.100247-eap04",
            "error_mismatch": false,
            "project": null,
            "timestamp": 1686584251.857629,
            "elapsed_time": 728.7499368190765,
            "x64": true,
            "actual_files_count": 1013,
            "expected_files_count": 1013,
            "repo_url": "https://github.com/cemu-project/Cemu",
            "commit_ref": "eda4cf4b241d56c5c16f6aa4d135b8a269676a76",
            "commit_message": "Fix UI crash on Windows (#813)\n\n",
            "commit_timestamp": 1683811665.0
        },
        {
            "tool_version": "232.0.20230608.100247-eap04",
            "error_mismatch": false,
            "project": null,
            "timestamp": 1686627921.276435,
            "elapsed_time": 1045.8493421077728,
            "x64": true,
            "actual_files_count": 1013,
            "expected_files_count": 1013,
            "repo_url": "https://github.com/cemu-project/Cemu",
            "commit_ref": "eda4cf4b241d56c5c16f6aa4d135b8a269676a76",
            "commit_message": "Fix UI crash on Windows (#813)\n\n",
            "commit_timestamp": 1683811665.0
        },
        {
            "tool_version": "232.0.20230608.100247-eap04",
            "error_mismatch": false,
            "project": null,
            "timestamp": 1686670702.552962,
            "elapsed_time": 814.1736767292023,
            "x64": true,
            "actual_files_count": 1013,
            "expected_files_count": 1013,
            "repo_url": "https://github.com/cemu-project/Cemu",
            "commit_ref": "eda4cf4b241d56c5c16f6aa4d135b8a269676a76",
            "commit_message": "Fix UI crash on Windows (#813)\n\n",
            "commit_timestamp": 1683811665.0
        },
        {
            "tool_version": "232.0.20230608.100247-eap04",
            "error_mismatch": false,
            "project": null,
            "timestamp": 1686714234.05156,
            "elapsed_time": 1024.5615365505219,
            "x64": true,
            "actual_files_count": 1013,
            "expected_files_count": 1013,
            "repo_url": "https://github.com/cemu-project/Cemu",
            "commit_ref": "eda4cf4b241d56c5c16f6aa4d135b8a269676a76",
            "commit_message": "Fix UI crash on Windows (#813)\n\n",
            "commit_timestamp": 1683811665.0
        },
        {
            "tool_version": "232.0.20230608.100247-eap04",
            "error_mismatch": false,
            "project": null,
            "timestamp": 1686757061.136996,
            "elapsed_time": 731.9500849246979,
            "x64": true,
            "actual_files_count": 1013,
            "expected_files_count": 1013,
            "repo_url": "https://github.com/cemu-project/Cemu",
            "commit_ref": "eda4cf4b241d56c5c16f6aa4d135b8a269676a76",
            "commit_message": "Fix UI crash on Windows (#813)\n\n",
            "commit_timestamp": 1683811665.0
        },
        {
            "tool_version": "232.0.20230608.100247-eap04",
            "error_mismatch": false,
            "project": null,
            "timestamp": 1686800590.837122,
            "elapsed_time": 878.0001707077026,
            "x64": true,
            "actual_files_count": 1013,
            "expected_files_count": 1013,
            "repo_url": "https://github.com/cemu-project/Cemu",
            "commit_ref": "eda4cf4b241d56c5c16f6aa4d135b8a269676a76",
            "commit_message": "Fix UI crash on Windows (#813)\n\n",
            "commit_timestamp": 1683811665.0
        },
        {
            "tool_version": "232.0.20230608.100247-eap04",
            "error_mismatch": false,
            "project": null,
            "timestamp": 1686843375.678549,
            "elapsed_time": 784.0646142959595,
            "x64": true,
            "actual_files_count": 1013,
            "expected_files_count": 1013,
            "repo_url": "https://github.com/cemu-project/Cemu",
            "commit_ref": "eda4cf4b241d56c5c16f6aa4d135b8a269676a76",
            "commit_message": "Fix UI crash on Windows (#813)\n\n",
            "commit_timestamp": 1683811665.0
        },
        {
            "tool_version": "232.0.20230608.100247-eap04",
            "error_mismatch": false,
            "project": null,
            "timestamp": 1686886689.669193,
            "elapsed_time": 742.6197426319122,
            "x64": true,
            "actual_files_count": 1013,
            "expected_files_count": 1013,
            "repo_url": "https://github.com/cemu-project/Cemu",
            "commit_ref": "eda4cf4b241d56c5c16f6aa4d135b8a269676a76",
            "commit_message": "Fix UI crash on Windows (#813)\n\n",
            "commit_timestamp": 1683811665.0
        },
        {
            "tool_version": "232.0.20230608.100247-eap04",
            "error_mismatch": false,
            "project": null,
            "timestamp": 1686930367.40337,
            "elapsed_time": 1104.669899225235,
            "x64": true,
            "actual_files_count": 1013,
            "expected_files_count": 1013,
            "repo_url": "https://github.com/cemu-project/Cemu",
            "commit_ref": "eda4cf4b241d56c5c16f6aa4d135b8a269676a76",
            "commit_message": "Fix UI crash on Windows (#813)\n\n",
            "commit_timestamp": 1683811665.0
        },
        {
            "tool_version": "232.0.20230613.111753-eap05",
            "error_mismatch": false,
            "project": null,
            "timestamp": 1686973083.378602,
            "elapsed_time": 767.5640444755554,
            "x64": true,
            "actual_files_count": 1013,
            "expected_files_count": 1013,
            "repo_url": "https://github.com/cemu-project/Cemu",
            "commit_ref": "eda4cf4b241d56c5c16f6aa4d135b8a269676a76",
            "commit_message": "Fix UI crash on Windows (#813)\n\n",
            "commit_timestamp": 1683811665.0
        },
        {
            "tool_version": "232.0.20230613.111753-eap05",
            "error_mismatch": false,
            "project": null,
            "timestamp": 1687016247.549784,
            "elapsed_time": 725.505007982254,
            "x64": true,
            "actual_files_count": 1013,
            "expected_files_count": 1013,
            "repo_url": "https://github.com/cemu-project/Cemu",
            "commit_ref": "eda4cf4b241d56c5c16f6aa4d135b8a269676a76",
            "commit_message": "Fix UI crash on Windows (#813)\n\n",
            "commit_timestamp": 1683811665.0
        },
        {
            "tool_version": "232.0.20230613.111753-eap05",
            "error_mismatch": false,
            "project": null,
            "timestamp": 1687060395.280605,
            "elapsed_time": 1113.4217100143433,
            "x64": true,
            "actual_files_count": 1013,
            "expected_files_count": 1013,
            "repo_url": "https://github.com/cemu-project/Cemu",
            "commit_ref": "eda4cf4b241d56c5c16f6aa4d135b8a269676a76",
            "commit_message": "Fix UI crash on Windows (#813)\n\n",
            "commit_timestamp": 1683811665.0
        },
        {
            "tool_version": "232.0.20230613.111753-eap05",
            "error_mismatch": false,
            "project": null,
            "timestamp": 1687102847.900633,
            "elapsed_time": 776.2240641117096,
            "x64": true,
            "actual_files_count": 1013,
            "expected_files_count": 1013,
            "repo_url": "https://github.com/cemu-project/Cemu",
            "commit_ref": "eda4cf4b241d56c5c16f6aa4d135b8a269676a76",
            "commit_message": "Fix UI crash on Windows (#813)\n\n",
            "commit_timestamp": 1683811665.0
        },
        {
            "tool_version": "232.0.20230613.111753-eap05",
            "error_mismatch": false,
            "project": null,
            "timestamp": 1687145888.776788,
            "elapsed_time": 723.5665347576141,
            "x64": true,
            "actual_files_count": 1013,
            "expected_files_count": 1013,
            "repo_url": "https://github.com/cemu-project/Cemu",
            "commit_ref": "eda4cf4b241d56c5c16f6aa4d135b8a269676a76",
            "commit_message": "Fix UI crash on Windows (#813)\n\n",
            "commit_timestamp": 1683811665.0
        },
        {
            "tool_version": "232.0.20230613.111753-eap05",
            "error_mismatch": false,
            "project": null,
            "timestamp": 1687189446.418091,
            "elapsed_time": 965.8116312026978,
            "x64": true,
            "actual_files_count": 1013,
            "expected_files_count": 1013,
            "repo_url": "https://github.com/cemu-project/Cemu",
            "commit_ref": "eda4cf4b241d56c5c16f6aa4d135b8a269676a76",
            "commit_message": "Fix UI crash on Windows (#813)\n\n",
            "commit_timestamp": 1683811665.0
        },
        {
            "tool_version": "232.0.20230613.111753-eap05",
            "error_mismatch": false,
            "project": null,
            "timestamp": 1687232307.661967,
            "elapsed_time": 837.3128623962402,
            "x64": true,
            "actual_files_count": 1013,
            "expected_files_count": 1013,
            "repo_url": "https://github.com/cemu-project/Cemu",
            "commit_ref": "eda4cf4b241d56c5c16f6aa4d135b8a269676a76",
            "commit_message": "Fix UI crash on Windows (#813)\n\n",
            "commit_timestamp": 1683811665.0
        },
        {
            "tool_version": "232.0.20230613.111753-eap05",
            "error_mismatch": false,
            "project": null,
            "timestamp": 1687275449.295138,
            "elapsed_time": 830.9712934494019,
            "x64": true,
            "actual_files_count": 1013,
            "expected_files_count": 1013,
            "repo_url": "https://github.com/cemu-project/Cemu",
            "commit_ref": "eda4cf4b241d56c5c16f6aa4d135b8a269676a76",
            "commit_message": "Fix UI crash on Windows (#813)\n\n",
            "commit_timestamp": 1683811665.0
        },
        {
            "tool_version": "232.0.20230613.111753-eap05",
            "error_mismatch": false,
            "project": null,
            "timestamp": 1687319172.891413,
            "elapsed_time": 1071.024983882904,
            "x64": true,
            "actual_files_count": 1013,
            "expected_files_count": 1013,
            "repo_url": "https://github.com/cemu-project/Cemu",
            "commit_ref": "eda4cf4b241d56c5c16f6aa4d135b8a269676a76",
            "commit_message": "Fix UI crash on Windows (#813)\n\n",
            "commit_timestamp": 1683811665.0
        },
        {
            "tool_version": "232.0.20230613.111753-eap05",
            "error_mismatch": false,
            "project": null,
            "timestamp": 1687362071.298487,
            "elapsed_time": 886.3652305603027,
            "x64": true,
            "actual_files_count": 1013,
            "expected_files_count": 1013,
            "repo_url": "https://github.com/cemu-project/Cemu",
            "commit_ref": "eda4cf4b241d56c5c16f6aa4d135b8a269676a76",
            "commit_message": "Fix UI crash on Windows (#813)\n\n",
            "commit_timestamp": 1683811665.0
        },
        {
            "tool_version": "232.0.20230613.111753-eap05",
            "error_mismatch": false,
            "project": null,
            "timestamp": 1687405114.269905,
            "elapsed_time": 735.9700193405151,
            "x64": true,
            "actual_files_count": 1013,
            "expected_files_count": 1013,
            "repo_url": "https://github.com/cemu-project/Cemu",
            "commit_ref": "eda4cf4b241d56c5c16f6aa4d135b8a269676a76",
            "commit_message": "Fix UI crash on Windows (#813)\n\n",
            "commit_timestamp": 1683811665.0
        },
        {
            "tool_version": "232.0.20230613.111753-eap05",
            "error_mismatch": false,
            "project": null,
            "timestamp": 1687448323.644278,
            "elapsed_time": 845.5833973884583,
            "x64": true,
            "actual_files_count": 1013,
            "expected_files_count": 1013,
            "repo_url": "https://github.com/cemu-project/Cemu",
            "commit_ref": "eda4cf4b241d56c5c16f6aa4d135b8a269676a76",
            "commit_message": "Fix UI crash on Windows (#813)\n\n",
            "commit_timestamp": 1683811665.0
        },
        {
            "tool_version": "232.0.20230613.111753-eap05",
            "error_mismatch": false,
            "project": null,
            "timestamp": 1687492438.956863,
            "elapsed_time": 923.9493975639343,
            "x64": true,
            "actual_files_count": 1013,
            "expected_files_count": 1013,
            "repo_url": "https://github.com/cemu-project/Cemu",
            "commit_ref": "eda4cf4b241d56c5c16f6aa4d135b8a269676a76",
            "commit_message": "Fix UI crash on Windows (#813)\n\n",
            "commit_timestamp": 1683811665.0
        }
    ]
}