{
    "v1": [
        {
            "tool_version": "231.0.20230404.121117",
            "error_mismatch": false,
            "project": null,
            "timestamp": 1683534457.703044,
            "elapsed_time": 53.7847580909729,
            "x64": false,
            "actual_files_count": 13,
            "expected_files_count": 13
        },
        {
            "tool_version": "231.0.20230404.121117",
            "error_mismatch": false,
            "project": null,
            "timestamp": 1683601696.097313,
            "elapsed_time": 53.703835010528564,
            "x64": false,
            "actual_files_count": 13,
            "expected_files_count": 13
        },
        {
            "tool_version": "231.0.20230404.121117",
            "error_mismatch": false,
            "project": null,
            "timestamp": 1683688153.323359,
            "elapsed_time": 72.39000225067139,
            "x64": false,
            "actual_files_count": 13,
            "expected_files_count": 13
        },
        {
            "tool_version": "231.0.20230404.121117",
            "error_mismatch": false,
            "project": null,
            "timestamp": 1683774605.496803,
            "elapsed_time": 81.3908863067627,
            "x64": false,
            "actual_files_count": 13,
            "expected_files_count": 13
        },
        {
            "tool_version": "231.0.20230404.121117",
            "error_mismatch": false,
            "project": null,
            "timestamp": 1683860939.59067,
            "elapsed_time": 69.38454222679138,
            "x64": false,
            "actual_files_count": 13,
            "expected_files_count": 13
        },
        {
            "tool_version": "231.0.20230404.121117",
            "error_mismatch": false,
            "project": null,
            "timestamp": 1683947324.177415,
            "elapsed_time": 73.66686534881592,
            "x64": false,
            "actual_files_count": 13,
            "expected_files_count": 13
        },
        {
            "tool_version": "231.0.20230404.121117",
            "error_mismatch": false,
            "project": null,
            "timestamp": 1684033726.565053,
            "elapsed_time": 59.179502964019775,
            "x64": false,
            "actual_files_count": 13,
            "expected_files_count": 13
        },
        {
            "tool_version": "231.0.20230404.121117",
            "error_mismatch": false,
            "project": null,
            "timestamp": 1684120226.790129,
            "elapsed_time": 88.71238398551941,
            "x64": false,
            "actual_files_count": 13,
            "expected_files_count": 13
        },
        {
            "tool_version": "232.0.20230509.135236-eap01",
            "error_mismatch": false,
            "project": null,
            "timestamp": 1684206595.809381,
            "elapsed_time": 85.91785860061646,
            "x64": false,
            "actual_files_count": 13,
            "expected_files_count": 13
        },
        {
            "tool_version": "232.0.20230509.135236-eap01",
            "error_mismatch": false,
            "project": null,
            "timestamp": 1684293004.751951,
            "elapsed_time": 74.83620476722717,
            "x64": false,
            "actual_files_count": 13,
            "expected_files_count": 13
        },
        {
            "tool_version": "232.0.20230509.135236-eap01",
            "error_mismatch": false,
            "project": null,
            "timestamp": 1684379344.123001,
            "elapsed_time": 67.69461870193481,
            "x64": false,
            "actual_files_count": 13,
            "expected_files_count": 13
        },
        {
            "tool_version": "232.0.20230509.135236-eap01",
            "error_mismatch": false,
            "project": null,
            "timestamp": 1684465704.350226,
            "elapsed_time": 54.157604455947876,
            "x64": false,
            "actual_files_count": 13,
            "expected_files_count": 13
        },
        {
            "tool_version": "232.0.20230509.135236-eap01",
            "error_mismatch": false,
            "project": null,
            "timestamp": 1684552140.844261,
            "elapsed_time": 77.36737203598022,
            "x64": false,
            "actual_files_count": 13,
            "expected_files_count": 13
        },
        {
            "tool_version": "232.0.20230509.135236-eap01",
            "error_mismatch": false,
            "project": null,
            "timestamp": 1684638488.9377,
            "elapsed_time": 54.792919397354126,
            "x64": false,
            "actual_files_count": 13,
            "expected_files_count": 13
        }
    ]
}